pylcanim/__init__.py
pylcanim/pylcanim.py
pylcanim-0.0.7.dist-info/LICENSE.txt
pylcanim-0.0.7.dist-info/METADATA
pylcanim-0.0.7.dist-info/WHEEL
pylcanim-0.0.7.dist-info/top_level.txt
pylcanim-0.0.7.dist-info/RECORD
