Metadata-Version: 2.1
Name: pylcanim
Version: 0.0.7
Summary: A simple library for loading animations made with SpriteFactory
Home-page: https://github.com/Lioncat2002/pylcanim
Author: lioncat2002
Author-email: gamedevcorp2002@gmail.com
License: UNKNOWN
Platform: UNKNOWN
Classifier: Programming Language :: Python :: 3
Classifier: License :: OSI Approved :: MIT License
Classifier: Operating System :: OS Independent
Requires-Python: >=3.8
